{
  "id": "princeton-m326m338n",
  "dct_title_s": "Hammonton, N. J. (Sheet 1)",
  "gbl_resourceClass_sm": [
    "Maps"
  ],
  "dct_accessRights_s": "Public",
  "gbl_mdVersion_s": "Aardvark",
  "dct_description_sm": [
    "\"Dec. 1886.\" Includes key and text. North oriented towards upper left."
  ],
  "dct_creator_sm": [
    "Sanborn Map Company"
  ],
  "dct_language_sm": [
    "en",
    "English"
  ],
  "dct_publisher_sm": [
    "New York : Sanborn Map & Publishing Co., Limited, 1886."
  ],
  "dct_subject_sm": [
    "Real property—New Jersey—Hammonton—Maps",
    "Hammonton (N.J.)—Maps",
    "Fire insurance maps—New Jersey—Hammonton—1886",
    "Maps—New Jersey—Hammonton—1886",
    "Maps"
  ],
  "dcat_theme_sm": [
    "Real property—New Jersey—Hammonton—Maps",
    "Hammonton (N.J.)—Maps",
    "Fire insurance maps—New Jersey—Hammonton—1886",
    "Maps—New Jersey—Hammonton—1886",
    "Maps"
  ],
  "dct_spatial_sm": [
    "New Jersey"
  ],
  "gbl_indexYear_im": [
    1886
  ],
  "gbl_mdModified_dt": "2025-11-17T19:34:12Z",
  "dct_references_s": "{\"http://schema.org/url\":\"https://catalog.princeton.edu/catalog/9952136923506421\",\"http://schema.org/downloadUrl\":\"https://figgy.princeton.edu/downloads/4bcabf40-b6da-4dc5-908f-52c19cbc18e7/file/70290491-5699-42b3-a53b-9c3ab0b05e8d\",\"http://schema.org/thumbnailUrl\":\"https://figgy.princeton.edu/downloads/4bcabf40-b6da-4dc5-908f-52c19cbc18e7/file/d5c963c6-f4c5-436c-8def-34d7bf7f4b46\",\"http://iiif.io/api/image\":\"https://iiif-cloud.princeton.edu/iiif/2/0a%2Ffd%2Fad%2F0afdad019d1a4b45b24e9786cf8e3930%2Fintermediate_file/info.json\",\"http://iiif.io/api/presentation#manifest\":\"https://figgy.princeton.edu/concern/scanned_maps/13596b2e-754d-4fa0-814d-cb5de2cc5529/manifest\"}",
  "gbl_resourceType_sm": [
    "Image"
  ],
  "dct_format_s": "TIFF",
  "gbl_suppressed_b": true,
  "dct_source_sm": [
    "princeton-0p0969835"
  ],
  "dct_identifier_sm": [
    "ark:/88435/m326m338n"
  ],
  "schema_provider_s": "Princeton",
  "locn_geometry": "ENVELOPE(-74.861, -74.676, 39.73, 39.583)",
  "dcat_bbox": "ENVELOPE(-74.861, -74.676, 39.73, 39.583)",
  "call_number_s": "HMC04 (Hammonton)",
  "rights_statement_s": "<a href=\"http://rightsstatements.org/vocab/NKC/1.0/\">No Known Copyright</a><br><p>Princeton University Library reasonably believes that the Item is not restricted by copyright or related rights, but a conclusive determination could not be made.\n<br/>You are free to use this Item in any way that is permitted by the copyright and related rights legislation that applies to your use.</p><p>Princeton University Library claims no copyright or license governing this digital resource. It is provided for free, on a non-commercial, open-access basis, for fair-use academic and research purposes only. Anyone who claims copyright over any part of these resources and feels that they should not be presented in this manner is invited to contact Princeton University Library, who will in turn consider such concerns and make every effort to respond appropriately. We request that users reproducing this resource cite it according to the guidelines described at <a href=\"https://library.princeton.edu/about/policies/special-collections-copyright-credit-and-citation-guidelines\">https://library.princeton.edu/about/policies/special-collections-copyright-credit-and-citation-guidelines</a>.\n</p>"
}