{
  "id": "princeton-dcdb78ts143",
  "dct_title_s": "Africa : Political Divisions. / Drawn & Engraved at Stanford's Geog. Establishment.",
  "gbl_resourceClass_sm": [
    "Maps"
  ],
  "dct_accessRights_s": "Public",
  "gbl_mdVersion_s": "Aardvark",
  "dct_description_sm": [
    "Relief shown by hachures. Map shows zones of: slave trade , import of arms and spirituous liquor, and prevailing religions; telegraph cable lines. Map shows administrative and political divisions colonial by treaty, and undefined international boundaries. Also, predominant religions. From book \"Africa Waiting or The Problem of Africa's Evangelization\" by Douglas M. Thor Bottom right, outside neatline: \"Engraved at Stanford's Geog. Establishment.\" Original map is filed in the Map/Geospatial Center, a map reproduction is attached to companion volume."
  ],
  "dct_creator_sm": [
    "Stanford, Edward, 1827-1904"
  ],
  "dct_language_sm": [
    "en"
  ],
  "dct_publisher_sm": [
    "London : Edward Stanford, 1897."
  ],
  "dct_subject_sm": [
    "Missions—Africa—Maps",
    "Administrative and political divisions—Maps",
    "Africa—Administrative and political divisions—Maps",
    "Africa",
    "Africa—Missions—Maps",
    "Africa—History—Maps",
    "thematic maps",
    "Thematic maps",
    "Maps"
  ],
  "dcat_theme_sm": [
    "Missions—Africa—Maps",
    "Administrative and political divisions—Maps",
    "Africa—Administrative and political divisions—Maps",
    "Africa",
    "Africa—Missions—Maps",
    "Africa—History—Maps",
    "thematic maps",
    "Thematic maps",
    "Maps"
  ],
  "dct_spatial_sm": [
    "Africa"
  ],
  "gbl_indexYear_im": [
    1897
  ],
  "gbl_mdModified_dt": "2025-11-17T19:39:02Z",
  "dct_references_s": "{\"http://schema.org/url\":\"https://catalog.princeton.edu/catalog/9968456473506421\",\"http://schema.org/downloadUrl\":\"https://figgy.princeton.edu/downloads/657a5af7-2e05-4bed-abad-25d2eeaf23e5/file/ac3653fa-0386-4d8e-9f9f-617899dadc25\",\"http://schema.org/thumbnailUrl\":\"https://figgy.princeton.edu/downloads/657a5af7-2e05-4bed-abad-25d2eeaf23e5/file/0b5450b1-764f-4284-97d4-6e4a4aab97bf\",\"http://iiif.io/api/image\":\"https://iiif-cloud.princeton.edu/iiif/2/c2%2F9c%2F64%2Fc29c647fa65b42759541e835c74dc10f%2Fintermediate_file/info.json\",\"http://iiif.io/api/presentation#manifest\":\"https://figgy.princeton.edu/concern/scanned_maps/338e3b81-68f3-49da-ae6b-5224e8179c4e/manifest\"}",
  "gbl_resourceType_sm": [
    "Image"
  ],
  "dct_format_s": "TIFF",
  "gbl_suppressed_b": false,
  "dct_identifier_sm": [
    "ark:/88435/dcdb78ts143"
  ],
  "schema_provider_s": "Princeton",
  "locn_geometry": "ENVELOPE(-17.540833, 51.288056, 37.363889, -34.834444)",
  "dcat_bbox": "ENVELOPE(-17.540833, 51.288056, 37.363889, -34.834444)",
  "call_number_s": "G8201.F33 1897 .S8",
  "rights_statement_s": "<a href=\"http://rightsstatements.org/vocab/CNE/1.0/\">Copyright Not Evaluated</a><br><p>The copyright and related rights status of this Item has not been evaluated.\n<br/>Please refer to the organization that has made the Item available for more information.\n<br/>You are free to use this Item in any way that is permitted by the copyright and related rights legislation that applies to your use.</p><p>Princeton University Library claims no copyright or license governing this digital resource. It is provided for free, on a non-commercial, open-access basis, for fair-use academic and research purposes only. Anyone who claims copyright over any part of these resources and feels that they should not be presented in this manner is invited to contact Princeton University Library, who will in turn consider such concerns and make every effort to respond appropriately. We request that users reproducing this resource cite it according to the guidelines described at <a href=\"https://library.princeton.edu/about/policies/special-collections-copyright-credit-and-citation-guidelines\">https://library.princeton.edu/about/policies/special-collections-copyright-credit-and-citation-guidelines</a>.\n</p>"
}