{
  "geoblacklight_version": "1.0",
  "dc_identifier_s": "ark:/88435/vx021m377",
  "layer_slug_s": "princeton-vx021m377",
  "uuid": "princeton-vx021m377",
  "dc_title_s": "Expanded map of Nairobi & suburbs",
  "solr_geom": "ENVELOPE(36.744722, 36.938611, -1.1925, -1.343056)",
  "dct_provenance_s": "Princeton",
  "dc_rights_s": "Restricted",
  "dc_description_s": "Includes index. Indexed map of Nairobi central business districts, map of Westlands area & shopping centre, map of Karen/Langata area and Nairobi National Park, and color illustrations on verso.",
  "dc_creator_sm": [
    "Tourist Maps Kenya Ltd"
  ],
  "dc_language_s": "eng",
  "dc_publisher_s": "Nairobi, Kenya : Tourist Maps Kenya Ltd., [1998]",
  "dc_subject_sm": [
    "Cities and towns—Kenya",
    "Central business districts—Kenya—Nairobi—Maps",
    "National parks and reserves—Kenya—Maps",
    "Nairobi (Kenya)—Maps",
    "Tourist maps"
  ],
  "dct_spatial_sm": [
    "Kenya"
  ],
  "solr_year_i": 1998,
  "layer_modified_dt": "2020-06-23T12:49:14Z",
  "layer_id_s": "ark:/88435/vx021m377",
  "dct_references_s": "{\"http://schema.org/url\":\"https://catalog.princeton.edu/catalog/5579793\",\"http://schema.org/thumbnailUrl\":\"https://figgy.princeton.edu/downloads/e8834b55-1e3f-4755-a638-9dc1299f37e2/file/797b5110-dee8-430a-86dd-e8499b067cbc\"}",
  "layer_geom_type_s": "Image",
  "suppressed_b": false,
  "call_number_s": "G8414.N2E635 [1998] .T6"
}