{
  "geoblacklight_version": "1.0",
  "dc_identifier_s": "ark:/88435/ns064751n",
  "layer_slug_s": "princeton-ns064751n",
  "uuid": "princeton-ns064751n",
  "dc_title_s": "Nepal Region Boundaries, 1989",
  "solr_geom": "ENVELOPE(80.055473, 88.201553, 30.442374, 26.354572)",
  "dct_provenance_s": "Princeton",
  "dc_rights_s": "Restricted",
  "dc_description_s": "This map includes the region boundaries of Nepal created by GfK MACON company, Germany.",
  "dc_creator_sm": [
    "GfK MACON"
  ],
  "dc_publisher_s": "Gfk MACON Company",
  "dc_subject_sm": [
    "Boundaries"
  ],
  "dct_spatial_sm": [
    "Nepal"
  ],
  "dct_temporal_sm": [
    "2006",
    "1989"
  ],
  "solr_year_i": 2006,
  "layer_modified_dt": "2018-06-13T19:01:05Z",
  "layer_id_s": "restricted-figgy:p-c252d0fa-d196-43c7-82c2-d783c5b5acc7",
  "dct_references_s": "{\"http://www.opengis.net/cat/csw/csdgm\":\"https://figgy.princeton.edu/downloads/f5b1969d-a8ab-4716-a0b1-3e255496e966/file/89e2e552-c69f-47de-937b-ee9bb8ba16dc\",\"http://schema.org/downloadUrl\":\"https://figgy.princeton.edu/downloads/c252d0fa-d196-43c7-82c2-d783c5b5acc7/file/74b4de8d-e72e-442f-902b-6817e2da7c9d\",\"http://schema.org/thumbnailUrl\":\"https://figgy.princeton.edu/downloads/c252d0fa-d196-43c7-82c2-d783c5b5acc7/file/99fbe3e3-d004-4105-99b4-e1f263f493eb\",\"http://www.opengis.net/def/serviceType/ogc/wms\":\"https://geoserver.princeton.edu/geoserver/restricted-figgy/wms\",\"http://www.opengis.net/def/serviceType/ogc/wfs\":\"https://geoserver.princeton.edu/geoserver/restricted-figgy/wfs\"}",
  "layer_geom_type_s": "Polygon",
  "dc_format_s": "Shapefile"
}