{
  "id": "princeton-0c483n27t",
  "dct_title_s": "Ocean Grove, West Ocean Grove, Bradley Beach, Bradley Park and Neptune City",
  "gbl_resourceClass_sm": [
    "Maps"
  ],
  "dct_accessRights_s": "Public",
  "gbl_mdVersion_s": "Aardvark",
  "dct_description_sm": [
    "Sheets 46, and 54 to 58 inclusive; issued in vol. 2 of New Jersey coast map series. Title from sheet 46. \"N.J.C.M. vol. 2.\" Includes key and text. North oriented toward upper left."
  ],
  "dct_creator_sm": [
    "Sanborn Map Company"
  ],
  "dct_language_sm": [
    "en",
    "English"
  ],
  "dct_publisher_sm": [
    "[New York] : [Sanborn Map Co.], [1905]",
    "[New York : Sanborn Map Co., 1905]"
  ],
  "dct_subject_sm": [
    "Real property—New Jersey—Ocean Grove—Maps",
    "Real property—New Jersey—West Ocean Grove—Maps",
    "Real property—New Jersey—Bradley Beach—Maps",
    "Real property—New Jersey—Neptune City—Maps",
    "Ocean Grove (N.J.)—Maps",
    "West Ocean Grove (N.J.)—Maps",
    "Bradley Beach (N.J.)—Maps",
    "Neptune City (N.J.)—Maps",
    "fire insurance maps",
    "Maps",
    "Fire insurance maps",
    "Real propery—New Jersey—Bradley Beach—Maps",
    "Real propery—New Jersey—Neptune City—Maps",
    "Real propery—New Jersey—West Ocean Grove—Maps"
  ],
  "dcat_theme_sm": [
    "Real property—New Jersey—Ocean Grove—Maps",
    "Real property—New Jersey—West Ocean Grove—Maps",
    "Real property—New Jersey—Bradley Beach—Maps",
    "Real property—New Jersey—Neptune City—Maps",
    "Ocean Grove (N.J.)—Maps",
    "West Ocean Grove (N.J.)—Maps",
    "Bradley Beach (N.J.)—Maps",
    "Neptune City (N.J.)—Maps",
    "fire insurance maps",
    "Maps",
    "Fire insurance maps",
    "Real propery—New Jersey—Bradley Beach—Maps",
    "Real propery—New Jersey—Neptune City—Maps",
    "Real propery—New Jersey—West Ocean Grove—Maps"
  ],
  "dct_spatial_sm": [
    "New Jersey"
  ],
  "gbl_indexYear_im": [
    1905
  ],
  "gbl_mdModified_dt": "2025-11-17T20:02:25Z",
  "dct_references_s": "{\"http://schema.org/url\":\"https://catalog.princeton.edu/catalog/9947944463506421\",\"http://schema.org/thumbnailUrl\":\"https://figgy.princeton.edu/downloads/a883158a-7cce-4143-ab57-e1954888fc57/file/654e2fb4-532a-43a6-a12c-75cfdcb16d13\",\"http://iiif.io/api/image\":\"https://iiif-cloud.princeton.edu/iiif/2/ae%2F80%2F5e%2Fae805e8f63e04fabb638c551ff8288a6%2Fintermediate_file/info.json\",\"http://iiif.io/api/presentation#manifest\":\"https://figgy.princeton.edu/concern/scanned_maps/a75e92a0-1364-4113-a724-1b0bb5d39f7d/manifest\"}",
  "gbl_resourceType_sm": [
    "Image"
  ],
  "gbl_suppressed_b": false,
  "dct_identifier_sm": [
    "ark:/88435/0c483n27t"
  ],
  "schema_provider_s": "Princeton",
  "locn_geometry": "ENVELOPE(-74.094, -74, 40.234, 40.183)",
  "dcat_bbox": "ENVELOPE(-74.094, -74, 40.234, 40.183)",
  "call_number_s": "HMC04 (Ocean Grove)",
  "rights_statement_s": "<a href=\"http://rightsstatements.org/vocab/NKC/1.0/\">No Known Copyright</a><br><p>Princeton University Library reasonably believes that the Item is not restricted by copyright or related rights, but a conclusive determination could not be made.\n<br/>You are free to use this Item in any way that is permitted by the copyright and related rights legislation that applies to your use.</p><p>Princeton University Library claims no copyright or license governing this digital resource. It is provided for free, on a non-commercial, open-access basis, for fair-use academic and research purposes only. Anyone who claims copyright over any part of these resources and feels that they should not be presented in this manner is invited to contact Princeton University Library, who will in turn consider such concerns and make every effort to respond appropriately. We request that users reproducing this resource cite it according to the guidelines described at <a href=\"https://library.princeton.edu/about/policies/special-collections-copyright-credit-and-citation-guidelines\">https://library.princeton.edu/about/policies/special-collections-copyright-credit-and-citation-guidelines</a>.\n</p>"
}