{
  "id": "princeton-dc73666g495",
  "dct_title_s": "Asia: Near East. GSGS 2555 (J-35 Izmir)",
  "gbl_resourceClass_sm": [
    "Maps"
  ],
  "dct_accessRights_s": "Public",
  "gbl_mdVersion_s": "Aardvark",
  "dct_description_sm": [
    "A scanned map object."
  ],
  "dct_creator_sm": [
    "United Kingdom. War Office"
  ],
  "dct_language_sm": [
    "English"
  ],
  "dct_spatial_sm": [
    "Turkey",
    "Izmir"
  ],
  "dct_temporal_sm": [
    "1916"
  ],
  "gbl_indexYear_im": [
    1916
  ],
  "gbl_mdModified_dt": "2025-11-04T16:48:33Z",
  "dct_references_s": "{\"http://schema.org/downloadUrl\":\"https://figgy.princeton.edu/downloads/46ad93d5-6f4c-4997-8817-abd897433fa5/file/d390ccc8-ccf2-4489-bdc4-616ad0b28347\",\"http://schema.org/thumbnailUrl\":\"https://figgy.princeton.edu/downloads/46ad93d5-6f4c-4997-8817-abd897433fa5/file/c60ca288-f0c1-4b8b-b628-4c5336de6dd3\",\"http://iiif.io/api/image\":\"https://iiif-cloud.princeton.edu/iiif/2/cc%2Fc3%2Fc9%2Fccc3c93b8f874633b700698e0fd2145b%2Fintermediate_file/info.json\",\"http://iiif.io/api/presentation#manifest\":\"https://figgy.princeton.edu/concern/scanned_maps/93f68734-289c-4368-9913-4611c50c5f19/manifest\"}",
  "gbl_resourceType_sm": [
    "Image"
  ],
  "dct_format_s": "TIFF",
  "gbl_suppressed_b": true,
  "dct_source_sm": [
    "princeton-dcr494vx13n"
  ],
  "dct_identifier_sm": [
    "ark:/88435/dc73666g495"
  ],
  "schema_provider_s": "Princeton",
  "locn_geometry": "ENVELOPE(24.000009, 30.000042, 40.000009, 36.000134)",
  "dcat_bbox": "ENVELOPE(24.000009, 30.000042, 40.000009, 36.000134)",
  "rights_statement_s": "<a href=\"http://rightsstatements.org/vocab/NoC-CR/1.0/\">No Copyright - Contractual Restrictions</a><br><p>Use of this Item is not restricted by copyright and/or related rights.\n<br/>As part of the acquisition or digitization of this Item, Princeton University Library is contractually required to limit the use of this Item. Limitations may include, but are not limited to, privacy issues, cultural protections, digitization agreements or donor agreements.</p><p>Princeton University Library claims no copyright or license governing this digital resource. It is provided for free, on a non-commercial, open-access basis, for fair-use academic and research purposes only. Anyone who claims copyright over any part of these resources and feels that they should not be presented in this manner is invited to contact Princeton University Library, who will in turn consider such concerns and make every effort to respond appropriately. We request that users reproducing this resource cite it according to the guidelines described at <a href=\"https://library.princeton.edu/about/policies/special-collections-copyright-credit-and-citation-guidelines\">https://library.princeton.edu/about/policies/special-collections-copyright-credit-and-citation-guidelines</a>.\n</p>"
}