{
  "geoblacklight_version": "1.0",
  "dc_identifier_s": "ark:/88435/np193d64r",
  "layer_slug_s": "princeton-np193d64r",
  "uuid": "princeton-np193d64r",
  "dc_title_s": "Dauphin County, Pennsylvania roads, 2014",
  "solr_geom": "ENVELOPE(-77.019294, -76.538117, 40.656076, 40.126777)",
  "dct_provenance_s": "Princeton",
  "dc_rights_s": "Restricted",
  "dc_description_s": "Roads and highways in Dauphin County, Pennsylvania, 2014.",
  "dc_creator_sm": [
    "Boundary Solutions, Inc."
  ],
  "dc_subject_sm": [
    "Transportation"
  ],
  "dct_spatial_sm": [
    "Dauphin",
    "Dauphin County",
    "Pennsylvania",
    "Harrisburg"
  ],
  "dct_temporal_sm": [
    "2014",
    "2012"
  ],
  "solr_year_i": 2014,
  "layer_modified_dt": "2018-06-13T18:34:56Z",
  "layer_id_s": "restricted-figgy:p-fdef31ee-6b6f-4e98-97b5-852b72e4858f",
  "dct_references_s": "{\"http://www.opengis.net/cat/csw/csdgm\":\"https://figgy.princeton.edu/downloads/bb7ffa80-f6af-4b88-bb1c-54dee2df5c5e/file/4a589aa7-1160-4ce0-8c86-de4b92754a21\",\"http://schema.org/downloadUrl\":\"https://figgy.princeton.edu/downloads/fdef31ee-6b6f-4e98-97b5-852b72e4858f/file/eb17852e-abc9-4cb8-87a1-ce15188a92ad\",\"http://schema.org/thumbnailUrl\":\"https://figgy.princeton.edu/downloads/fdef31ee-6b6f-4e98-97b5-852b72e4858f/file/7de3e46b-9616-4104-9a04-c0932e0e1da3\",\"http://www.opengis.net/def/serviceType/ogc/wms\":\"https://geoserver.princeton.edu/geoserver/restricted-figgy/wms\",\"http://www.opengis.net/def/serviceType/ogc/wfs\":\"https://geoserver.princeton.edu/geoserver/restricted-figgy/wfs\"}",
  "layer_geom_type_s": "Line",
  "dc_format_s": "Shapefile"
}