{
  "id": "princeton-np193c65t",
  "dct_title_s": "Gallia transalpina in suas quatuor provincias, Narbonensem, Aquitaniam, Lugudensem et Belgicam descripta",
  "gbl_resourceClass_sm": [
    "Maps"
  ],
  "dct_accessRights_s": "Public",
  "gbl_mdVersion_s": "Aardvark",
  "dct_description_sm": [
    "Shows ancient Gaul divided into four Roman provinces. Relief shown pictorially. In upper right-hand corner: 5. \"Cum privilegio S.C. Maj.\" Plate 5 from: Descriptio orbis antiqui in XLIV tabulis exhibita / J.D. Köhler ... Norimbergæ : Studio atque opera C. Weigelii, [1720?]"
  ],
  "dct_creator_sm": [
    "Weigel, Christoph, 1654-1725"
  ],
  "dct_language_sm": [
    "la",
    "Latin"
  ],
  "dct_publisher_sm": [
    "Norib. [Nuremberg] : excudit C. Weigelius, [1720]"
  ],
  "dct_subject_sm": [
    "France—Historical geography—Maps—Early works to 1800",
    "France—Maps—Early works to 1800",
    "Gaul—Maps—Early works to 1800",
    "Historical maps—France",
    "Maps"
  ],
  "dcat_theme_sm": [
    "France—Historical geography—Maps—Early works to 1800",
    "France—Maps—Early works to 1800",
    "Gaul—Maps—Early works to 1800",
    "Historical maps—France",
    "Maps"
  ],
  "dct_spatial_sm": [
    "France"
  ],
  "gbl_indexYear_im": [
    1720
  ],
  "gbl_mdModified_dt": "2025-11-17T19:18:55Z",
  "dct_references_s": "{\"http://schema.org/url\":\"https://catalog.princeton.edu/catalog/9971354943506421\",\"http://schema.org/downloadUrl\":\"https://figgy.princeton.edu/downloads/67b65d80-8197-4150-803d-fabb7d06cfb3/file/d4ea6356-d2ac-4d2b-9966-d877051d73b0\",\"http://schema.org/thumbnailUrl\":\"https://figgy.princeton.edu/downloads/67b65d80-8197-4150-803d-fabb7d06cfb3/file/43bf05bd-db6f-4802-bf58-a2f258cd3317\",\"http://iiif.io/api/image\":\"https://iiif-cloud.princeton.edu/iiif/2/00%2F31%2F73%2F0031739ec8e84ad99cdc25dd0a031008%2Fintermediate_file/info.json\",\"http://iiif.io/api/presentation#manifest\":\"https://figgy.princeton.edu/concern/scanned_maps/385e0e21-266e-457a-912f-e55a476a38f9/manifest\"}",
  "gbl_resourceType_sm": [
    "Image"
  ],
  "dct_format_s": "TIFF",
  "gbl_suppressed_b": false,
  "dct_identifier_sm": [
    "ark:/88435/np193c65t"
  ],
  "schema_provider_s": "Princeton",
  "locn_geometry": "ENVELOPE(-8.69, 8.58, 53, 41.92)",
  "dcat_bbox": "ENVELOPE(-8.69, 8.58, 53, 41.92)",
  "call_number_s": "D Alcove 20, Drawer 1 HMC01.4328",
  "rights_statement_s": "<a href=\"http://rightsstatements.org/vocab/NKC/1.0/\">No Known Copyright</a><br><p>Princeton University Library reasonably believes that the Item is not restricted by copyright or related rights, but a conclusive determination could not be made.\n<br/>You are free to use this Item in any way that is permitted by the copyright and related rights legislation that applies to your use.</p><p>Princeton University Library claims no copyright or license governing this digital resource. It is provided for free, on a non-commercial, open-access basis, for fair-use academic and research purposes only. Anyone who claims copyright over any part of these resources and feels that they should not be presented in this manner is invited to contact Princeton University Library, who will in turn consider such concerns and make every effort to respond appropriately. We request that users reproducing this resource cite it according to the guidelines described at <a href=\"https://library.princeton.edu/about/policies/special-collections-copyright-credit-and-citation-guidelines\">https://library.princeton.edu/about/policies/special-collections-copyright-credit-and-citation-guidelines</a>.\n</p>"
}