{
  "geoblacklight_version": "1.0",
  "dc_identifier_s": "ark:/88435/2z10wv01q",
  "layer_slug_s": "princeton-2z10wv01q",
  "uuid": "princeton-2z10wv01q",
  "dc_title_s": "Atlas of New Jersey (page 30)",
  "solr_geom": "ENVELOPE(-75.5633859, -73.8939789, 41.357423, 38.7911303)",
  "dct_provenance_s": "Princeton",
  "dc_rights_s": "Public",
  "dc_description_s": "Cover title. Scale of maps 1-17: 1 mile to an inch. At head of title : Geological Survey of New Jersey.",
  "dc_creator_sm": [
    "Geological Survey of New Jersey"
  ],
  "dc_language_s": "eng",
  "dc_publisher_s": "New York, Julius Bien & Co., [1884-1888]",
  "dc_subject_sm": [
    "New Jersey—Maps, Topographic"
  ],
  "layer_modified_dt": "2018-08-24T18:28:56Z",
  "layer_id_s": "public-figgy:p-dc8cedb5-d075-4d40-ac25-8d100ab85f8b",
  "dct_references_s": "{\"http://schema.org/url\":\"https://catalog.princeton.edu/catalog/1943935\",\"http://schema.org/downloadUrl\":\"https://figgy.princeton.edu/downloads/dc8cedb5-d075-4d40-ac25-8d100ab85f8b/file/8868712b-b5c3-40fe-8108-7d3144fc0b09\",\"http://schema.org/thumbnailUrl\":\"https://figgy.princeton.edu/downloads/dc8cedb5-d075-4d40-ac25-8d100ab85f8b/file/2010e5f6-3a9a-4aec-a703-c34072d55cda\",\"http://iiif.io/api/image\":\"https://libimages1.princeton.edu/loris/figgy_prod/85%2F58%2Fbb%2F8558bb9cd76442d99935d2a33e830b14%2Fintermediate_file.jp2/info.json\",\"http://iiif.io/api/presentation#manifest\":\"https://figgy.princeton.edu/concern/scanned_maps/f2bc60c7-7807-4b8b-992a-0aa74b564ff2/manifest\"}",
  "layer_geom_type_s": "Image",
  "dc_format_s": "TIFF",
  "suppressed_b": true,
  "dc_source_sm": [
    "princeton-p2676w91q"
  ],
  "call_number_s": "Oversize 8565.672.12e"
}