{
  "geoblacklight_version": "1.0",
  "dc_identifier_s": "ark:/88435/000001473",
  "layer_slug_s": "princeton-000001473",
  "uuid": "princeton-000001473",
  "dc_title_s": "Keyport, Monmouth County, New Jersey : including South Keyport (Sheet 8)",
  "solr_geom": "ENVELOPE(-74.219, -74.183, 40.448, 40.423)",
  "dct_provenance_s": "Princeton",
  "dc_rights_s": "Public",
  "dc_description_s": "\"Aug. 1923.\" Includes location map, key, streets and specials index, and text. Title from index sheet. \"1225.\"",
  "dc_creator_sm": [
    "Sanborn Map Company"
  ],
  "dc_language_s": "eng",
  "dc_publisher_s": "New York : Sanborn Map Company, 1923.",
  "dc_subject_sm": [
    "Real property—New Jersey—Keyport—Maps",
    "Real property—New Jersey—South Keyport—Maps",
    "Keyport (N.J.)—Maps",
    "South Keyport (N.J.)—Maps",
    "Fire insurance maps—New Jersey—Keyport—1923",
    "Fire insurance maps—New Jersey—South Keyport—1923",
    "Maps—New Jersey—Keyport—1923",
    "Maps—New Jersey—South Keyport—1923"
  ],
  "dct_spatial_sm": [
    "New Jersey"
  ],
  "solr_year_i": 1923,
  "layer_modified_dt": "2020-06-23T15:09:22Z",
  "layer_id_s": "public-figgy:p-b3a6d12e-2901-44b5-9dca-59e4eb316c3c",
  "dct_references_s": "{\"http://schema.org/url\":\"https://catalog.princeton.edu/catalog/4806188\",\"http://schema.org/downloadUrl\":\"https://figgy.princeton.edu/downloads/b3a6d12e-2901-44b5-9dca-59e4eb316c3c/file/230a1ef8-fff0-4649-847c-776b108aacc4\",\"http://schema.org/thumbnailUrl\":\"https://figgy.princeton.edu/downloads/b3a6d12e-2901-44b5-9dca-59e4eb316c3c/file/0b0934b2-232d-46be-9402-3f2d0c966c47\",\"http://iiif.io/api/image\":\"https://iiif-cloud.princeton.edu/iiif/2/fd%2F79%2F7b%2Ffd797bbb6de9489c8892c10dcd32c4f6%2Fintermediate_file/info.json\",\"http://iiif.io/api/presentation#manifest\":\"https://figgy.princeton.edu/concern/scanned_maps/157b718e-18a8-4bdf-82d3-c2e5ac456636/manifest\"}",
  "layer_geom_type_s": "Image",
  "dc_format_s": "TIFF",
  "suppressed_b": true,
  "dc_source_sm": [
    "princeton-dr26z129f"
  ],
  "call_number_s": "HMC04 (Keyport)"
}