{
  "geoblacklight_version": "1.0",
  "dc_identifier_s": "ark:/88435/pg15bj24g",
  "layer_slug_s": "princeton-pg15bj24g",
  "uuid": "princeton-pg15bj24g",
  "dc_title_s": "Pasco County, Florida land parcels, 2014",
  "solr_geom": "ENVELOPE(-82.850395, -82.054878, 28.478788, 28.171194)",
  "dct_provenance_s": "Princeton",
  "dc_rights_s": "Restricted",
  "dc_description_s": "Land parcels in Pasco County, Florida, 2014.",
  "dc_creator_sm": [
    "Boundary Solutions, Inc."
  ],
  "dc_subject_sm": [
    "Planning and Cadastral"
  ],
  "dct_spatial_sm": [
    "Florida",
    "Pasco",
    "Pasco County",
    "Tampa"
  ],
  "dct_temporal_sm": [
    "2014",
    "2013",
    "2013"
  ],
  "solr_year_i": 2014,
  "layer_modified_dt": "2020-05-21T02:24:52Z",
  "layer_id_s": "restricted-figgy:p-773db1bb-1240-45f6-a0d2-8f8891e613a4",
  "dct_references_s": "{\"http://www.opengis.net/cat/csw/csdgm\":\"https://figgy.princeton.edu/downloads/f3218187-c125-4861-bf07-9f2a69e8d307/file/3bbd61b9-43fe-4816-b968-62a8665a18e5\",\"http://schema.org/downloadUrl\":\"https://figgy.princeton.edu/downloads/773db1bb-1240-45f6-a0d2-8f8891e613a4/file/ceec5462-07b2-45be-9193-48831da771f0\",\"http://schema.org/thumbnailUrl\":\"https://figgy.princeton.edu/downloads/773db1bb-1240-45f6-a0d2-8f8891e613a4/file/13afaa1e-b6d9-420d-9d67-c73324e1600b\",\"http://www.opengis.net/def/serviceType/ogc/wms\":\"https://geoserver.princeton.edu/geoserver/restricted-figgy/wms\",\"http://www.opengis.net/def/serviceType/ogc/wfs\":\"https://geoserver.princeton.edu/geoserver/restricted-figgy/wfs\"}",
  "layer_geom_type_s": "Polygon",
  "dc_format_s": "Shapefile",
  "dct_issued_dt": "2013-01-01T00:00:00Z",
  "suppressed_b": false
}