{
  "geoblacklight_version": "1.0",
  "dc_identifier_s": "ark:/88435/xs55mg45g",
  "layer_slug_s": "princeton-xs55mg45g",
  "uuid": "princeton-xs55mg45g",
  "dc_title_s": "China county map, 1958",
  "solr_geom": "ENVELOPE(68.196555, 136.429552, 54.139796, 5.036617)",
  "dct_provenance_s": "Princeton",
  "dc_rights_s": "Restricted",
  "dc_description_s": "Map of administrative divisions in China, at the county level and above, for the year 1958.",
  "dc_creator_sm": [
    "All China Marketing Research Co., Ltd."
  ],
  "dc_subject_sm": [
    "Boundaries"
  ],
  "dct_spatial_sm": [
    "China"
  ],
  "dct_temporal_sm": [
    "1958",
    "2016"
  ],
  "solr_year_i": 1958,
  "layer_modified_dt": "2020-05-21T02:32:11Z",
  "layer_id_s": "restricted-figgy:p-94d2fa11-4083-4a15-b4ea-5d972f05239f",
  "dct_references_s": "{\"http://www.opengis.net/cat/csw/csdgm\":\"https://figgy.princeton.edu/downloads/033b18fc-94c7-41ec-ab40-4c3f595bf8ae/file/a631e97d-1147-47f4-bb6e-d93696b60666\",\"http://schema.org/downloadUrl\":\"https://figgy.princeton.edu/downloads/94d2fa11-4083-4a15-b4ea-5d972f05239f/file/c85272b5-3d36-4fb0-bd04-4ae3257368c7\",\"http://schema.org/thumbnailUrl\":\"https://figgy.princeton.edu/downloads/94d2fa11-4083-4a15-b4ea-5d972f05239f/file/89c074ef-fb5d-4519-b2a1-254431b1e2e2\",\"http://www.opengis.net/def/serviceType/ogc/wms\":\"https://geoserver.princeton.edu/geoserver/restricted-figgy/wms\",\"http://www.opengis.net/def/serviceType/ogc/wfs\":\"https://geoserver.princeton.edu/geoserver/restricted-figgy/wfs\"}",
  "layer_geom_type_s": "Polygon",
  "dc_format_s": "Shapefile",
  "dct_issued_dt": "2016-01-01T00:00:00Z",
  "suppressed_b": false
}