{
  "geoblacklight_version": "1.0",
  "dc_identifier_s": "ark:/88435/6682x6860",
  "layer_slug_s": "princeton-6682x6860",
  "uuid": "princeton-6682x6860",
  "dc_title_s": "Stanhope, Sussex County, New Jersey",
  "solr_geom": "ENVELOPE(-74.720272, -74.683246, 40.926068, 40.899141)",
  "dct_provenance_s": "Princeton",
  "dc_rights_s": "Public",
  "dc_description_s": "\"September 1920.\" Includes location map, key, key map, specials index, and text. \"3304.\"",
  "dc_creator_sm": [
    "Sanborn Map Company"
  ],
  "dc_language_s": "eng",
  "dc_publisher_s": "New York : Sanborn Map Company, 1920.",
  "dc_subject_sm": [
    "Real property—New Jersey—Stanhope—Maps",
    "Stanhope (N.J.)—Maps"
  ],
  "dct_spatial_sm": [
    "New Jersey"
  ],
  "layer_modified_dt": "2019-06-04T17:59:16Z",
  "layer_id_s": "ark:/88435/6682x6860",
  "dct_references_s": "{\"http://schema.org/url\":\"https://catalog.princeton.edu/catalog/5609860\",\"http://schema.org/thumbnailUrl\":\"https://figgy.princeton.edu/downloads/463f4b91-12d4-4774-8dc9-26a85c96f502/file/070758c3-3ea6-4049-a2d8-e327697e6c0d\",\"http://iiif.io/api/image\":\"https://iiif.princeton.edu/loris/figgy_prod/4a%2F71%2F4e%2F4a714ecb549b48b589c0809b54e9761f%2Fintermediate_file.jp2/info.json\",\"http://iiif.io/api/presentation#manifest\":\"https://figgy.princeton.edu/concern/scanned_maps/049c9d33-d84b-46a7-beff-7695167ce3a0/manifest\"}",
  "layer_geom_type_s": "Image",
  "call_number_s": "HMC04 (Stanhope)"
}