{
  "geoblacklight_version": "1.0",
  "dc_identifier_s": "ark:/88435/05741v221",
  "layer_slug_s": "princeton-05741v221",
  "uuid": "princeton-05741v221",
  "dc_title_s": "Venetianische Kriegs-Begebenheiten",
  "solr_geom": "ENVELOPE(21.683374, 22.40006, 37.341774, 36.662772)",
  "dct_provenance_s": "Princeton",
  "dc_rights_s": "Public",
  "dc_description_s": "Relief shown pictorially. Shows the Gulf of Messenia and surrounding region during the military campaigns of Venetian general Francesco Morosini during the Morean War (1684-1699). Text below map: Nachdem der Venetianische General Capitain Morosini die Vestung Coron erobert ...",
  "dc_language_s": "deu",
  "dc_publisher_s": "[Germany? : s.n., ca. 1690]",
  "dc_subject_sm": [
    "Morosini, Francesco, 1618 or 1619-1694—Military leadership—Maps—Early works to 1800",
    "Messēnia (Greece)—Maps—Early works to 1800",
    "Messenia, Gulf of (Greece)—Maps—Early works to 1800",
    "Venice (Italy)—History—Turkish Wars, 17th century—Maps—Early works to 1800"
  ],
  "dct_spatial_sm": [
    "Greece",
    "Italy"
  ],
  "layer_modified_dt": "2019-02-12T17:27:53Z",
  "layer_id_s": "public-figgy:p-44d89a8a-e4e4-41eb-877d-d4c35573d87e",
  "dct_references_s": "{\"http://schema.org/url\":\"https://catalog.princeton.edu/catalog/8165657\",\"http://schema.org/downloadUrl\":\"https://figgy.princeton.edu/downloads/44d89a8a-e4e4-41eb-877d-d4c35573d87e/file/8a492795-59b1-4c29-aa77-9ba198f356ea\",\"http://schema.org/thumbnailUrl\":\"https://figgy.princeton.edu/downloads/44d89a8a-e4e4-41eb-877d-d4c35573d87e/file/d26ee092-5153-4fb9-a0f3-94a861e7b27f\",\"http://iiif.io/api/image\":\"https://libimages1.princeton.edu/loris/figgy_prod/55%2Fe7%2F90%2F55e7902771a1419cb0a0e6b40d790e9f%2Fintermediate_file.jp2/info.json\",\"http://iiif.io/api/presentation#manifest\":\"https://figgy.princeton.edu/concern/scanned_maps/94d93ed0-eafd-4cc9-9ea8-0723f5b84e90/manifest\"}",
  "layer_geom_type_s": "Image",
  "dc_format_s": "TIFF",
  "call_number_s": "HMC01.7085"
}