{
  "geoblacklight_version": "1.0",
  "dc_identifier_s": "ark:/88435/g158bk009",
  "layer_slug_s": "princeton-g158bk009",
  "uuid": "princeton-g158bk009",
  "dc_title_s": "The Rand McNally new commercial atlas map of New York",
  "solr_geom": "ENVELOPE(-79.76666666666667, -71.85, 45.016666666666666, 40.5)",
  "dct_provenance_s": "Princeton",
  "dc_rights_s": "Public",
  "dc_description_s": "Rand McNally & Co. Inset : southeast area map continued. Map shows railroads and steamship lines. Principal cities are listed and located. List of New York railroads. Verso: New York counties, creeks, islands, lakes and ponds, mountains, rivers, and towns. New York electric lines.",
  "dc_language_s": "eng",
  "dc_publisher_s": "[Chicago] : Rand McNally & Co., 1914.",
  "dc_subject_sm": [
    "Administrative and political divisions",
    "Steamboat lines",
    "Railroads",
    "New York—Maps"
  ],
  "layer_modified_dt": "2018-06-07T06:42:08Z",
  "layer_id_s": "public-figgy:5d73d825-81a2-4c1e-8ab4-84bc3e482cad",
  "dct_references_s": "{\"http://schema.org/url\":\"https://catalog.princeton.edu/catalog/6515127\",\"http://schema.org/downloadUrl\":\"https://figgy.princeton.edu/downloads/5d73d825-81a2-4c1e-8ab4-84bc3e482cad/file/8c145e91-4a1e-4c08-a122-a759415406ba\",\"http://schema.org/thumbnailUrl\":\"https://figgy.princeton.edu/downloads/5d73d825-81a2-4c1e-8ab4-84bc3e482cad/file/37719dd8-9ffa-4097-bee6-81b63500f577\",\"http://iiif.io/api/image\":\"https://libimages1.princeton.edu/loris/figgy_prod/fb%2F0c%2F07%2Ffb0c07b2fa534eeaa6b247e0a1edb165%2Fintermediate_file.jp2/info.json\",\"http://iiif.io/api/presentation#manifest\":\"https://figgy.princeton.edu/concern/scanned_maps/86a93cba-dd75-4aff-bbe6-940c1aa4eb06/manifest\"}",
  "layer_geom_type_s": "Image",
  "dc_format_s": "TIFF"
}