{
  "geoblacklight_version": "1.0",
  "dc_identifier_s": "ark:/88435/5425kc62t",
  "layer_slug_s": "princeton-5425kc62t",
  "uuid": "princeton-5425kc62t",
  "dc_title_s": "Cape May City : including Cape May Point, South Cape May and West Cape May, Cape May County, New Jersey (Sheet 14)",
  "solr_geom": "ENVELOPE(-74.938801, -74.871605, 38.950125, 38.928588)",
  "dct_provenance_s": "Princeton",
  "dc_rights_s": "Public",
  "dc_description_s": "Includes key and text. \"N.J.C.M. vol. 4.\" Historic Maps copy has sheets 1 and 4-25 of N.J. coast map series, vol. 4.",
  "dc_creator_sm": [
    "Sanborn Map Company"
  ],
  "dc_language_s": "eng",
  "dc_publisher_s": "New York : Sanborn Map Company, 1909.",
  "dc_subject_sm": [
    "Real property—New Jersey—Cape May—Maps",
    "Real property—New Jersey—South Cape May—Maps",
    "Real property—New Jersey—West Cape May—Maps",
    "Cape May (N.J.)—Maps",
    "South Cape May (N.J. : Borough)—Maps",
    "West Cape May (N.J.)—Maps"
  ],
  "dct_spatial_sm": [
    "New Jersey"
  ],
  "layer_modified_dt": "2018-10-30T00:16:13Z",
  "layer_id_s": "public-figgy:p-8c33b94e-bc75-4736-9469-1b6b1df4a5cb",
  "dct_references_s": "{\"http://schema.org/url\":\"https://catalog.princeton.edu/catalog/5321092\",\"http://schema.org/downloadUrl\":\"https://figgy.princeton.edu/downloads/8c33b94e-bc75-4736-9469-1b6b1df4a5cb/file/62009d6f-d765-444a-bed9-f0abb786a72c\",\"http://schema.org/thumbnailUrl\":\"https://figgy.princeton.edu/downloads/8c33b94e-bc75-4736-9469-1b6b1df4a5cb/file/a15df557-aef8-448b-a243-f0d8b4a7252c\",\"http://iiif.io/api/image\":\"https://libimages1.princeton.edu/loris/figgy_prod/4e%2F90%2F58%2F4e90582d6dfe4566a9cc77e0535f137f%2Fintermediate_file.jp2/info.json\",\"http://iiif.io/api/presentation#manifest\":\"https://figgy.princeton.edu/concern/scanned_maps/0ab3e217-712d-42ca-85ef-b3a81dfd533c/manifest\"}",
  "layer_geom_type_s": "Image",
  "dc_format_s": "TIFF",
  "suppressed_b": true,
  "dc_source_sm": [
    "princeton-9019s537m"
  ],
  "call_number_s": "HMC04 (Cape May)"
}