{
  "geoblacklight_version": "1.0",
  "dc_identifier_s": "ark:/88435/8910jw15x",
  "layer_slug_s": "princeton-8910jw15x",
  "uuid": "princeton-8910jw15x",
  "dc_title_s": "Arapahoe County, Colorado land parcels, 2010",
  "solr_geom": "ENVELOPE(-105.054115, -103.706575, 39.740463, 39.563702)",
  "dct_provenance_s": "Princeton",
  "dc_rights_s": "Restricted",
  "dc_description_s": "Land parcels in Arapahoe County, Colorado, 2010.",
  "dc_creator_sm": [
    "Boundary Solutions, Inc."
  ],
  "dc_subject_sm": [
    "Planning and Cadastral"
  ],
  "dct_spatial_sm": [
    "Colorado",
    "Arapahoe County",
    "Denver",
    "Aurora",
    "Centennial"
  ],
  "dct_temporal_sm": [
    "2010",
    "2010"
  ],
  "solr_year_i": 2010,
  "layer_modified_dt": "2020-05-21T02:26:19Z",
  "layer_id_s": "restricted-figgy:p-27f9a450-0279-48aa-ad6d-328bd2d58182",
  "dct_references_s": "{\"http://www.opengis.net/cat/csw/csdgm\":\"https://figgy.princeton.edu/downloads/40f94c17-f2df-4246-9057-4b8e978db059/file/26f5374f-a4ec-4a89-a024-94ef882b72e5\",\"http://schema.org/downloadUrl\":\"https://figgy.princeton.edu/downloads/27f9a450-0279-48aa-ad6d-328bd2d58182/file/0a92f901-d40a-436e-a637-e1c09eee5c5f\",\"http://schema.org/thumbnailUrl\":\"https://figgy.princeton.edu/downloads/27f9a450-0279-48aa-ad6d-328bd2d58182/file/4f82cd16-a8df-4e7d-8564-415459dfeb3c\",\"http://www.opengis.net/def/serviceType/ogc/wms\":\"https://geoserver.princeton.edu/geoserver/restricted-figgy/wms\",\"http://www.opengis.net/def/serviceType/ogc/wfs\":\"https://geoserver.princeton.edu/geoserver/restricted-figgy/wfs\"}",
  "layer_geom_type_s": "Polygon",
  "dc_format_s": "Shapefile",
  "dct_issued_dt": "2010-01-01T00:00:00Z",
  "suppressed_b": false
}