{
  "geoblacklight_version": "1.0",
  "dc_identifier_s": "ark:/88435/xp68kj71v",
  "layer_slug_s": "princeton-xp68kj71v",
  "uuid": "princeton-xp68kj71v",
  "dc_title_s": "Specialkarte vom Fichtelgebirge",
  "solr_geom": "ENVELOPE(11.433362, 12.266778, 50.337696, 49.858474)",
  "dct_provenance_s": "Princeton",
  "dc_rights_s": "Public",
  "dc_description_s": "Map of the Fichtelgebirge mountains in the German state of Bavaria. Relief shown by shading. Probably issued in: Führer durch das Fichtelgebirge ... Würzburg ; Wien : Verlag von Leo Woerl, 1891.",
  "dc_creator_sm": [
    "Woerl, Leo, 1843-1918"
  ],
  "dc_language_s": "deu",
  "dc_publisher_s": "Würzburg ; Wien : Verlag v. Leo Woerl, [1891] (Wien : Kartogr. Anst. v. G. Freytag & Berndt)",
  "dc_subject_sm": [
    "Bavaria (Germany)—Maps",
    "Fichtelgebirge (Germany and Czech Republic)—Maps",
    "Maps—Germany—Bavaria—1891",
    "Maps—Germany—Fichtelgebirge—1891"
  ],
  "dct_spatial_sm": [
    "Germany"
  ],
  "solr_year_i": 1891,
  "layer_modified_dt": "2020-06-22T22:38:36Z",
  "layer_id_s": "public-figgy:p-c44f8ad4-d709-4aad-9349-a7a4efa68a42",
  "dct_references_s": "{\"http://schema.org/url\":\"https://catalog.princeton.edu/catalog/7420499\",\"http://schema.org/downloadUrl\":\"https://figgy.princeton.edu/downloads/c44f8ad4-d709-4aad-9349-a7a4efa68a42/file/c0f81a98-30b3-43a4-bcf3-2b28f048a5ab\",\"http://schema.org/thumbnailUrl\":\"https://figgy.princeton.edu/downloads/c44f8ad4-d709-4aad-9349-a7a4efa68a42/file/ae2838a8-6df1-4088-bc60-28d592aaf88e\",\"http://iiif.io/api/image\":\"https://iiif-cloud.princeton.edu/iiif/2/c7%2F64%2Fdc%2Fc764dc67df02422e8e9e445314bed67b%2Fintermediate_file/info.json\",\"http://iiif.io/api/presentation#manifest\":\"https://figgy.princeton.edu/concern/scanned_maps/828cf873-f175-41a3-b700-9b6b1ee96ca1/manifest\"}",
  "layer_geom_type_s": "Image",
  "dc_format_s": "TIFF",
  "suppressed_b": false,
  "call_number_s": "HMC01.3291"
}