{
  "geoblacklight_version": "1.0",
  "dc_identifier_s": "ark:/88435/v979v476g",
  "layer_slug_s": "princeton-v979v476g",
  "uuid": "princeton-v979v476g",
  "dc_title_s": "Congo, 1990",
  "solr_geom": "ENVELOPE(12.0, 18.0, 2.0, -4.0)",
  "dct_provenance_s": "Princeton",
  "dc_rights_s": "Public",
  "dc_description_s": "This is a map of the Peoples Republic of the Congo, shown at a 1:2,490,000 scale. The map was created by the United States Central Intelligence Agency.",
  "dc_creator_sm": [
    "Central Intelligence Agency"
  ],
  "dc_publisher_s": "Central Intelligence Agency",
  "dc_subject_sm": [
    "Roads",
    "Railroads",
    "Airfield",
    "Administrational and Political Boundaries"
  ],
  "dct_spatial_sm": [
    "Congo",
    "Africa"
  ],
  "dct_temporal_sm": [
    "1971"
  ],
  "solr_year_i": 1971,
  "layer_modified_dt": "2018-02-24T00:22:05Z",
  "layer_id_s": "public-figgy:2dba382d-ebf5-4e54-a1ce-51c3eb5f82ab",
  "dct_references_s": "{\"http://www.opengis.net/cat/csw/csdgm\":\"https://figgy.princeton.edu/downloads/eebfd8ec-1ea9-4294-8ddb-7287fddbde3e/file/2a538e12-81bf-44ae-8ae2-47ea7d06048f\",\"http://schema.org/downloadUrl\":\"https://figgy.princeton.edu/downloads/2dba382d-ebf5-4e54-a1ce-51c3eb5f82ab/file/5a6e6248-8564-4f6b-99cb-f0bea15d364e\",\"http://schema.org/thumbnailUrl\":\"https://figgy.princeton.edu/downloads/2dba382d-ebf5-4e54-a1ce-51c3eb5f82ab/file/5a9cf598-508c-4fa2-b64a-88805e32d435\",\"http://iiif.io/api/image\":\"https://libimages1.princeton.edu/loris/figgy_prod/cd%2F6f%2F02%2Fcd6f02d49a3f464b849af3b5eda7f9e6%2Fintermediate_file.jp2/info.json\",\"http://iiif.io/api/presentation#manifest\":\"https://figgy.princeton.edu/concern/scanned_maps/460fcf30-6faa-4b1a-8031-3daa5f1548a7/manifest\"}",
  "layer_geom_type_s": "Image",
  "dc_format_s": "TIFF"
}