{
  "geoblacklight_version": "1.0",
  "dc_identifier_s": "ark:/88435/h702q822w",
  "layer_slug_s": "princeton-h702q822w",
  "uuid": "princeton-h702q822w",
  "dc_title_s": "L'America divisa ne'suoi principali stati di nuovo projezione",
  "solr_geom": "ENVELOPE(-180.0, 180.0, 80.0, -80.0)",
  "dct_provenance_s": "Princeton",
  "dc_rights_s": "Public",
  "dc_description_s": "Relief shown by hachures. Shows also the Pacific Ocean to New Zealand. Below title: Venezia 1776. Possibly from Zatta's Atlante novissima. [1788]. Includes text and ill.",
  "dc_creator_sm": [
    "Zatta, Antonio, active 1757-1797"
  ],
  "dc_language_s": "ita",
  "dc_publisher_s": "Venezia : Antonio Zatta, [1776?]",
  "dc_subject_sm": [
    "America—Maps—Early works to 1800",
    "Pacific Ocean—Maps—Early works to 1800"
  ],
  "layer_modified_dt": "2018-06-22T23:04:35Z",
  "layer_id_s": "public-figgy:p-cb2c8d9d-5c67-46c8-a3f2-70308b296141",
  "dct_references_s": "{\"http://schema.org/url\":\"https://catalog.princeton.edu/catalog/4761120\",\"http://schema.org/downloadUrl\":\"https://figgy.princeton.edu/downloads/cb2c8d9d-5c67-46c8-a3f2-70308b296141/file/f8a4da05-a5d5-4b13-8e13-afdaf12e6ffc\",\"http://schema.org/thumbnailUrl\":\"https://figgy.princeton.edu/downloads/cb2c8d9d-5c67-46c8-a3f2-70308b296141/file/9ff8acdb-ddbd-45c9-8c80-58feb70002f5\",\"http://iiif.io/api/image\":\"https://libimages1.princeton.edu/loris/figgy_prod/ab%2F7b%2Fc2%2Fab7bc226b9fb427a9d543013b29c1e04%2Fintermediate_file.jp2/info.json\",\"http://iiif.io/api/presentation#manifest\":\"https://figgy.princeton.edu/concern/scanned_maps/a2181034-6f1a-4d6b-8273-8ea125aabb13/manifest\"}",
  "layer_geom_type_s": "Image",
  "dc_format_s": "TIFF",
  "call_number_s": "HMC01.106"
}