{
  "geoblacklight_version": "1.0",
  "dc_identifier_s": "ark:/88435/8g84mp75t",
  "layer_slug_s": "princeton-8g84mp75t",
  "uuid": "princeton-8g84mp75t",
  "dc_title_s": "The extended road from Oakham to Richmond in Yorkshire",
  "solr_geom": "ENVELOPE(-1.757457, -0.707576, 54.413655, 52.656727)",
  "dct_provenance_s": "Princeton",
  "dc_rights_s": "Public",
  "dc_description_s": "Relief shown pictorially and by hachures. Strip map, showing road in 7 segments, with numbered distances along road. \"Comencing at Oakham aforesaid & extending to Barnsley in Yorksh. : containing 81 miles 1 furlong vizt. From Oakham to Milton Mowbray 10.'4. to Plumtree 12.'6. to Nottingham 5.'2. to Papplewick 7'.5. to Mansfeild 6.'1. to Clown 11.'3 to Aughton 9.'.3. to Rotherum .4'4. to Wombwell 8.'.. & to Barnsley 4.'4.\" From: Britannia, volume the first, or, An illustration of the Kingdom of England and dominion of Wales. London : Printed by the author ..., 1675. Inside lower right border: 48. Plate is numbered, indicating it is probably from the 1st ed., 3d issue of Britannia. cf. M. Schuchard, A descriptive bibliography of the works of John Ogilby and William Morgan.",
  "dc_creator_sm": [
    "Ogilby, John, 1600-1676"
  ],
  "dc_language_s": "eng",
  "dc_publisher_s": "[London : J. Ogilby, 1675]",
  "dc_subject_sm": [
    "Roads—England—Yorkshire—Maps—Early works to 1800",
    "Yorkshire—Maps—Early works to 1800"
  ],
  "dct_spatial_sm": [
    "England"
  ],
  "solr_year_i": 1675,
  "layer_modified_dt": "2020-05-21T02:55:20Z",
  "layer_id_s": "public-figgy:p-e8e7e60e-4950-4a19-8adc-1e791bc7fc8d",
  "dct_references_s": "{\"http://schema.org/url\":\"https://catalog.princeton.edu/catalog/7280804\",\"http://schema.org/downloadUrl\":\"https://figgy.princeton.edu/downloads/e8e7e60e-4950-4a19-8adc-1e791bc7fc8d/file/36c09f09-ceca-40c5-b0f4-a7b78066d922\",\"http://schema.org/thumbnailUrl\":\"https://figgy.princeton.edu/downloads/e8e7e60e-4950-4a19-8adc-1e791bc7fc8d/file/47d24539-e642-4aac-9092-ec9b3640a0da\",\"http://iiif.io/api/image\":\"https://iiif-cloud.princeton.edu/iiif/2/7e%2F6f%2F2f%2F7e6f2f4884b241e1b78e269270284ed4%2Fintermediate_file/info.json\",\"http://iiif.io/api/presentation#manifest\":\"https://figgy.princeton.edu/concern/scanned_maps/00d54ec9-9a49-4c98-baf2-20325c407a0d/manifest\"}",
  "layer_geom_type_s": "Image",
  "dc_format_s": "TIFF",
  "suppressed_b": false,
  "call_number_s": "HMC01.4804"
}