{
  "geoblacklight_version": "1.0",
  "dc_identifier_s": "ark:/88435/1r66j456m",
  "layer_slug_s": "princeton-1r66j456m",
  "uuid": "princeton-1r66j456m",
  "dc_title_s": "Clarke County, Georgia land parcels, 2011",
  "solr_geom": "ENVELOPE(-83.536531, -83.240834, 34.039461, 33.847686)",
  "dct_provenance_s": "Princeton",
  "dc_rights_s": "Restricted",
  "dc_description_s": "Land parcels in Clarke County, Georgia, 2011.",
  "dc_creator_sm": [
    "Boundary Solutions, Inc."
  ],
  "dc_subject_sm": [
    "Planning and Cadastral"
  ],
  "dct_spatial_sm": [
    "Clarke",
    "Clarke County",
    "Georgia",
    "Athens"
  ],
  "dct_temporal_sm": [
    "2011",
    "2006"
  ],
  "solr_year_i": 2011,
  "layer_modified_dt": "2018-06-13T18:24:30Z",
  "layer_id_s": "restricted-figgy:p-6e43d6cc-e861-4a6e-a91e-14dea5f8a2db",
  "dct_references_s": "{\"http://www.opengis.net/cat/csw/csdgm\":\"https://figgy.princeton.edu/downloads/75fc352b-7cfb-42b9-85e0-f680075d5d92/file/840dffb7-fe3e-447c-88c8-c613485ff91b\",\"http://schema.org/downloadUrl\":\"https://figgy.princeton.edu/downloads/6e43d6cc-e861-4a6e-a91e-14dea5f8a2db/file/1a3f8150-65de-4f3e-a903-bceb0be7cf13\",\"http://schema.org/thumbnailUrl\":\"https://figgy.princeton.edu/downloads/6e43d6cc-e861-4a6e-a91e-14dea5f8a2db/file/d769866b-0725-4675-b092-0bad1201bcf1\",\"http://www.opengis.net/def/serviceType/ogc/wms\":\"https://geoserver.princeton.edu/geoserver/restricted-figgy/wms\",\"http://www.opengis.net/def/serviceType/ogc/wfs\":\"https://geoserver.princeton.edu/geoserver/restricted-figgy/wfs\"}",
  "layer_geom_type_s": "Polygon",
  "dc_format_s": "Shapefile"
}