{
  "geoblacklight_version": "1.0",
  "dc_identifier_s": "ark:/88435/jh343v10r",
  "layer_slug_s": "princeton-jh343v10r",
  "uuid": "princeton-jh343v10r",
  "dc_title_s": "Carte geologique detaillee de la France [a 1/80 000]: St. Lo.",
  "solr_geom": "ENVELOPE(-1.6362, -0.7543, 49.4601, 49.1005)",
  "dct_provenance_s": "Princeton",
  "dc_rights_s": "Public",
  "dc_description_s": "France. Service de la carte geologique de France North Decimal Degree 49.4601 South Decimal Degree 49.1005 East Decimal Degree -0.7543 West Decimal Degree -1.6362 Relief shown by hachures. Principal meridian: Paris. Longitude is given in centesimal values (100 grades = 90 degrees) .The Service de la carte geologique de la France was integrated to the BRGM to become the only France Service geologique national. Based on \"Carte topograqphique de l'etat major.\"",
  "dc_language_s": "fra",
  "dc_publisher_s": "Orléans : Bureau de recherches géogiques et minières, 1926.",
  "dc_subject_sm": [
    "Geology",
    "Mines and mineral resources",
    "France—Maps"
  ],
  "layer_modified_dt": "2018-06-07T05:49:06Z",
  "layer_id_s": "public-figgy:76582f4d-eed5-4512-ace7-d7fa59433f34",
  "dct_references_s": "{\"http://schema.org/url\":\"https://figgy.princeton.edu/concern/scanned_maps/86f69254-bfd7-48ce-83f8-1346441c2ef7\",\"http://schema.org/downloadUrl\":\"https://figgy.princeton.edu/downloads/76582f4d-eed5-4512-ace7-d7fa59433f34/file/c25b7013-3023-42e5-9ac1-018f1bf23659\",\"http://schema.org/thumbnailUrl\":\"https://figgy.princeton.edu/downloads/76582f4d-eed5-4512-ace7-d7fa59433f34/file/4e92381c-a570-4872-b276-dd5f2a21c96e\",\"http://iiif.io/api/image\":\"https://libimages1.princeton.edu/loris/figgy_prod/a9%2Fcc%2Ffb%2Fa9ccfbc562c5481289696038bfe104be%2Fintermediate_file.jp2/info.json\",\"http://iiif.io/api/presentation#manifest\":\"https://figgy.princeton.edu/concern/scanned_maps/86f69254-bfd7-48ce-83f8-1346441c2ef7/manifest\"}",
  "layer_geom_type_s": "Image",
  "dc_format_s": "TIFF"
}